README.md
setup.py
data/__init__.py
stratipy/__init__.py
stratipy/biostat.py
stratipy/biostat_go.py
stratipy/biostat_plot.py
stratipy/consensus_clustering.py
stratipy/filtering_diffusion.py
stratipy/formatting_data.py
stratipy/hierarchical_clustering.py
stratipy/load_data.py
stratipy/nbs.py
stratipy/nbs_class.py
stratipy/nbs_cluster.py
stratipy/nbs_local.py
stratipy/nmf_bootstrap.py
stratipy/pac.py
stratipy/parameters.py
stratipy.egg-info/PKG-INFO
stratipy.egg-info/SOURCES.txt
stratipy.egg-info/dependency_links.txt
stratipy.egg-info/top_level.txt
test/__init__.py
test/test_filtering_diffusion.py