Metadata-Version: 1.1
Name: stratipy
Version: 0.8
Summary: Patients stratification with Graph-regularized Non-negative Matrix Factorization (GNMF) in Python.
Home-page: https://github.com/GHFC/StratiPy
Author: Yang-Min KIM, Guillaume DUMAS
Author-email: yang-min.kim@pasteur.fr, guillaume.dumas@pasteur.fr
License: BSD
Keywords: bioinformatics graph network stratification
Platform: UNKNOWN
Classifier: Development Status :: 4 - Beta
Classifier: Topic :: Scientific/Engineering :: Bio-Informatics
Classifier: License :: OSI Approved :: BSD License
